setup.py
gmail_client/__init__.py
gmail_client/exceptions.py
gmail_client/gmail.py
gmail_client/mailbox.py
gmail_client/message.py
gmail_client.egg-info/PKG-INFO
gmail_client.egg-info/SOURCES.txt
gmail_client.egg-info/dependency_links.txt
gmail_client.egg-info/top_level.txt
gmail_client/codecs/__init__.py
gmail_client/codecs/utf7.py