Metadata-Version: 1.1
Name: gmail-client
Version: 0.0.7.7
Summary: A Pythonic interface for Google Mail. Based of https://github.com/charlierguo/gmai
Home-page: https://github.com/wilbertom/gmail
Author: Wilberto Morales
Author-email: wilbertomorales777@gmail.com
License: MIT
Keywords: google gmail client
Platform: UNKNOWN
Classifier: Topic :: Communications :: Email
Classifier: License :: OSI Approved :: MIT License
